spinqit/__init__.py
spinqit/spinq_backends.cp39-win_amd64.pyd
spinqit/algorithm/__init__.py
spinqit/algorithm/amplitude_estimation.py
spinqit/algorithm/chemistry.py
spinqit/algorithm/coined_quantum_walk.py
spinqit/algorithm/grover_seach.py
spinqit/algorithm/hhl.py
spinqit/algorithm/iterative_amplitude_estimation.py
spinqit/algorithm/ml_amplitude_estimation.py
spinqit/algorithm/qaoa.py
spinqit/algorithm/qsvc.py
spinqit/algorithm/quantum_counting.py
spinqit/algorithm/random_circuit.py
spinqit/algorithm/shor.py
spinqit/algorithm/vqe.py
spinqit/algorithm/loss/__init__.py
spinqit/algorithm/loss/measurement.py
spinqit/algorithm/loss/quantum_loss.py
spinqit/algorithm/optimizer/__init__.py
spinqit/algorithm/optimizer/adam.py
spinqit/algorithm/optimizer/gradientdescent.py
spinqit/algorithm/optimizer/optimizer.py
spinqit/algorithm/optimizer/quantumnaturalgradient.py
spinqit/algorithm/optimizer/scipy_optim.py
spinqit/algorithm/optimizer/spsa.py
spinqit/algorithm/optimizer/torch_optim.py
spinqit/algorithm/optimizer/utils.py
spinqit/backend/__init__.py
spinqit/backend/backend.py
spinqit/backend/backend_util.py
spinqit/backend/basebackend.py
spinqit/backend/basic_simulator_backend.py
spinqit/backend/nmr_backend.py
spinqit/backend/pytorch_backend.py
spinqit/backend/qasm_backend.py
spinqit/backend/spinq_cloud_backend.py
spinqit/backend/client/__init__.py
spinqit/backend/client/spinq_cloud_client.py
spinqit/backend/client/spinq_session.py
spinqit/backend/layout/__init__.py
spinqit/backend/layout/layout.py
spinqit/backend/layout/layout_util.py
spinqit/backend/layout/physical_layout.py
spinqit/backend/layout/routing_layout.py
spinqit/backend/layout/sven_swap_mapper.py
spinqit/compiler/__init__.py
spinqit/compiler/compiler.py
spinqit/compiler/ir.py
spinqit/compiler/native_compiler.py
spinqit/compiler/qasm_compiler.py
spinqit/compiler/qiskit_compiler.py
spinqit/compiler/decomposer/ZYZdecomposer.py
spinqit/compiler/decomposer/__init__.py
spinqit/compiler/decomposer/diagonal.py
spinqit-0.2.3.dist-info/METADATA
spinqit-0.2.3.dist-info/WHEEL
spinqit-0.2.3.dist-info/top_level.txt
spinqit-0.2.3.dist-info/RECORD
